langchain/__init__.py
langchain/base_language.py
langchain/cache.py
langchain/env.py
langchain/example_generator.py
langchain/formatting.py
langchain/globals.py
langchain/hub.py
langchain/input.py
langchain/model_laboratory.py
langchain/py.typed
langchain/python.py
langchain/requests.py
langchain/serpapi.py
langchain/sql_database.py
langchain/text_splitter.py
langchain/_api/__init__.py
langchain/_api/deprecation.py
langchain/_api/interactive_env.py
langchain/_api/module_import.py
langchain/_api/path.py
langchain/adapters/__init__.py
langchain/adapters/openai.py
langchain/agents/__init__.py
langchain/agents/agent.py
langchain/agents/agent_iterator.py
langchain/agents/agent_types.py
langchain/agents/initialize.py
langchain/agents/load_tools.py
langchain/agents/loading.py
langchain/agents/schema.py
langchain/agents/tools.py
langchain/agents/types.py
langchain/agents/utils.py
langchain/agents/agent_toolkits/__init__.py
langchain/agents/agent_toolkits/azure_cognitive_services.py
langchain/agents/agent_toolkits/base.py
langchain/agents/agent_toolkits/ainetwork/__init__.py
langchain/agents/agent_toolkits/ainetwork/toolkit.py
langchain/agents/agent_toolkits/amadeus/toolkit.py
langchain/agents/agent_toolkits/clickup/__init__.py
langchain/agents/agent_toolkits/clickup/toolkit.py
langchain/agents/agent_toolkits/conversational_retrieval/__init__.py
langchain/agents/agent_toolkits/conversational_retrieval/openai_functions.py
langchain/agents/agent_toolkits/conversational_retrieval/tool.py
langchain/agents/agent_toolkits/csv/__init__.py
langchain/agents/agent_toolkits/file_management/__init__.py
langchain/agents/agent_toolkits/file_management/toolkit.py
langchain/agents/agent_toolkits/github/__init__.py
langchain/agents/agent_toolkits/github/toolkit.py
langchain/agents/agent_toolkits/gitlab/__init__.py
langchain/agents/agent_toolkits/gitlab/toolkit.py
langchain/agents/agent_toolkits/gmail/__init__.py
langchain/agents/agent_toolkits/gmail/toolkit.py
langchain_aipy-0.3.21.dist-info/METADATA
langchain_aipy-0.3.21.dist-info/WHEEL
langchain_aipy-0.3.21.dist-info/top_level.txt
langchain_aipy-0.3.21.dist-info/RECORD
