Metadata-Version: 2.4
Name: langchain-aipy
Version: 0.3.21
Summary: Building applications with LLMs through composability
Author-email: The QPYPI Team <qpypi@qpython.org>
License: MIT AND (Apache-2.0 OR BSD-2-Clause)
Project-URL: Homepage, https://qpypi.qpython.org/project/langchain-aipy/
Classifier: Intended Audience :: Developers
Classifier: Intended Audience :: Education
Classifier: Intended Audience :: Information Technology
Classifier: Intended Audience :: End Users/Desktop
Classifier: License :: OSI Approved :: Apache Software License
Classifier: Operating System :: Android
Classifier: Programming Language :: Python
Classifier: Programming Language :: Python :: 3.12
Classifier: Topic :: Software Development
Requires-Python: ==3.12.*
Requires-Dist: langchain-community-aipy
Requires-Dist: langchain-text-splitters-aipy
Requires-Dist: pydantic-qpython
Requires-Dist: greenlet-qpython
Requires-Dist: mypy-extensions
Requires-Dist: jsonpatch
Requires-Dist: annotated-types
Requires-Dist: tenacity
Requires-Dist: aiohttp-qpython
Requires-Dist: numpy-aipy
Requires-Dist: langsmith-aipy
Requires-Dist: sqlalchemy-qpython
Requires-Dist: langchain-core-aipy
Requires-Dist: langchain-openai-aipy
